{
    "category": "hadith",
    "en": {
        "title": "HADITH 14 : The value of human life",
        "text": "Abdullah bin Masud narrated that the messenger of Allah said :'The blood of a Muslim may not be legally spilt other than in one of three [instances] : the married person who commits adultery; a life for a life; and one who forsakes his religion and abandons the community.'it was related by Bukhari and Muslim",
        "video": [
            {
                "sheikh": "Sheikh Uthman Ibn Farooq",
                "video": "https://www.youtube.com/embed/h4n4D0ipcsk?start=1154"
            }
        ]
    },
    "ar": {
        "title": "الحديث الرابع عشر: متى يهدر دم المسلم",
        "text": "عنْ ابنِ مسعودٍ رَضِي اللهُ عَنْهُ قالَ: قالَ رسولُ اللهِ صَلَّى اللهُ عَلَيْهِ وَسَلَّمَ: {لاَ يَحِلُّ دَمُ امْرِئٍ مُسْلِمٍ يَشْهَدُ أَن لاَ إِلَهَ إِلاَّ اللهُ وأَنِّي رسُولُ اللهِ إِلاَّ بِإِحْدَى ثَلاَثٍ: الثَّيِّبِ الزَّانِي، وَالنَّفْسِ بِالنَّفْسِ، وَالتَّارِكِ لِدِينِهِ الْمُفَارِقِ لِلْجَمَاعَةِ}.رواه البخاريُّ ومسلمٌ.",
        "video": [
            {
                "sheikh": "الشيخ عثمان الخميس",
                "video": "https://www.youtube.com/embed/RryHKlo6ubk"
            }
        ]
    },
    "no": 14
}